.DS_Store
tspecscores/__init__.py
tspecscores/_nbdev.py
tspecscores/tspecscores.py
tspecscores-0.0.2.dist-info/LICENSE
tspecscores-0.0.2.dist-info/METADATA
tspecscores-0.0.2.dist-info/WHEEL
tspecscores-0.0.2.dist-info/entry_points.txt
tspecscores-0.0.2.dist-info/top_level.txt
tspecscores-0.0.2.dist-info/RECORD
