Metadata-Version: 2.1
Name: tspecscores
Version: 0.0.2
Summary: test
Home-page: https://github.com/morriso1/tspecscores/tree/main/
Author: Otto Morris
Author-email: ottomorris@gmail.com
License: Apache Software License 2.0
Keywords: gene expression tissue specificity metrics
Platform: UNKNOWN
Classifier: Development Status :: 3 - Alpha
Classifier: Intended Audience :: Developers
Classifier: Natural Language :: English
Classifier: Programming Language :: Python :: 3.6
Classifier: Programming Language :: Python :: 3.7
Classifier: Programming Language :: Python :: 3.8
Classifier: License :: OSI Approved :: Apache Software License
Requires-Python: >=3.6
License-File: LICENSE
Requires-Dist: numpy
Requires-Dist: pandas
